skytap/__init__.py
skytap/fixtures.py
skytap_fixtures-1.0.7.dist-info/DESCRIPTION.rst
skytap_fixtures-1.0.7.dist-info/METADATA
skytap_fixtures-1.0.7.dist-info/RECORD
skytap_fixtures-1.0.7.dist-info/WHEEL
skytap_fixtures-1.0.7.dist-info/metadata.json
skytap_fixtures-1.0.7.dist-info/top_level.txt
