Metadata-Version: 2.0
Name: skytap-fixtures
Version: 1.0.7
Summary: A library to glue functions that produce test fixtures to the tests that use them.
Home-page: UNKNOWN
Author: Skytap, Inc.
Author-email: UNKNOWN
License: UNKNOWN
Platform: UNKNOWN
